neurohep/__init__.py
neurohep/detection.py
neurohep/preprocessing.py
neurohep/visualization.py
NeuroHEP-0.1.0.dist-info/LICENSE.txt
NeuroHEP-0.1.0.dist-info/METADATA
NeuroHEP-0.1.0.dist-info/WHEEL
NeuroHEP-0.1.0.dist-info/top_level.txt
NeuroHEP-0.1.0.dist-info/RECORD
