Metadata-Version: 2.2
Name: NeuroHEP
Version: 0.1.0
Summary: A package for detecting Heartbeat Evoked Potentials (HEPs) in EEG signals
Author-email: Mahsa Alidadi <mahsa.alidadii@example.com>
License: MIT
Project-URL: Homepage, https://github.com/mahsaalidadi/NeuroHEP
Project-URL: Source, https://github.com/mahsaalidadi/NeuroHEP
Project-URL: Tracker, https://github.com/mahsaalidadi/NeuroHEP/issues
Requires-Python: >=3.7
License-File: LICENSE.txt
Requires-Dist: numpy
Requires-Dist: scipy
Requires-Dist: matplotlib
Requires-Dist: mne
Requires-Dist: neurokit2
Requires-Dist: pandas
